{
  "build": {
    "production": {
      "releaseChannel": "production",
      "env": {
        "API_URL": "https://api.new.refugies.info",
        "SITE_URL": "https://refugies.info",
        "ALGOLIA_INDEX": "prod_refugies",
        "ENV_NAME": "PROD"
      }
    },
    "preview": {
      "releaseChannel": "staging",
      "env": {
        "API_URL": "https://api.new.refugies.info",
        "SITE_URL": "https://refugies.info",
        "ALGOLIA_INDEX": "prod_refugies",
        "ENV_NAME": "STAGING"
      },
      "android": {
        "buildType": "apk"
      },
      "ios": {
        "simulator": true
      }
    }
  },
  "cli": {
    "version": ">= 0.35.0",
    "requireCommit": true
  },
  "submit": {
    "production": {
      "android": {
        "serviceAccountKeyPath": "./refugies-info-appkey.json",
        "track": "internal",
        "releaseStatus": "draft"
      },
      "ios": {
        "appleId": "matthieu.fesselier@gmail.com",
        "ascAppId": "1595597429",
        "appleTeamId": "98K762J2MM"
      }
    }
  }
}
